CHANGES.txt
LICENSE.txt
MANIFEST.in
README.md
Requirements.txt
setup.py
titantools/__init__.py
titantools/data_science.py
titantools/decorators.py
titantools/filesystem.py
titantools/network.py
titantools/orm.py
titantools/plist.py
titantools/system.py
titantools/utilities.py
titantools.egg-info/PKG-INFO
titantools.egg-info/SOURCES.txt
titantools.egg-info/dependency_links.txt
titantools.egg-info/top_level.txt